Spire.Doc.Free-12.12.0.dist-info/METADATA
Spire.Doc.Free-12.12.0.dist-info/RECORD
Spire.Doc.Free-12.12.0.dist-info/WHEEL
Spire.Doc.Free-12.12.0.dist-info/top_level.txt
spire/__init__.py
spire/doc/AttrCollection.py
spire/doc/AutoFitBehaviorType.py
spire/doc/Background.py
spire/doc/BackgroundGradient.py
spire/doc/BackgroundType.py
spire/doc/Body.py
spire/doc/BodyRegion.py
spire/doc/BodyRegionCollection.py
spire/doc/Bookmark.py
spire/doc/BookmarkCollection.py
spire/doc/BookmarkEnd.py
spire/doc/BookmarkLevel.py
spire/doc/BookmarkStart.py
spire/doc/BookmarkTextStyle.py
spire/doc/BookmarksNavigator.py
spire/doc/Border.py
spire/doc/BorderStyle.py
spire/doc/Borders.py
spire/doc/Break.py
spire/doc/BreakType.py
spire/doc/BuiltInProperty.py
spire/doc/BuiltinDocumentProperties.py
spire/doc/BuiltinStyle.py
spire/doc/BuiltinStyleLoader.py
spire/doc/CalendarType.py
spire/doc/CaptionNumberingFormat.py
spire/doc/CaptionPosition.py
spire/doc/CellCollection.py
spire/doc/CellFormat.py
spire/doc/CellMerge.py
spire/doc/CellWidthType.py
spire/doc/ChangeItems.py
spire/doc/ChangeItemsType.py
spire/doc/CharacterFormat.py
spire/doc/CharacterSpacing.py
spire/doc/CheckBoxFormField.py
spire/doc/CheckBoxSizeType.py
spire/doc/ClipboardData.py
spire/doc/CollectionEx.py
spire/doc/Column.py
spire/doc/ColumnCollection.py
spire/doc/Comment.py
spire/doc/CommentDisplayMode.py
spire/doc/CommentFormat.py
spire/doc/CommentMark.py
spire/doc/CommentMarkType.py
spire/doc/CommentsCollection.py
spire/doc/CompareOptions.py
spire/doc/ControlField.py
spire/doc/CssStyleSheetType.py
spire/doc/CustomDocumentProperties.py
spire/doc/CustomXmlPart.py
spire/doc/CustomXmlPartCollection.py
spire/doc/DLSException.py
spire/doc/DefaultTableStyle.py
spire/doc/DifferRevisions.py
spire/doc/DigitalSignatureType.py
spire/doc/DocOleObject.py
spire/doc/DocPicture.py
spire/doc/Doc_PropertyType.py
spire/doc/Document.py
spire/doc/DocumentBase.py
spire/doc/DocumentContainer.py
spire/doc/DocumentLayoutOptions.py
spire/doc/DocumentObject.py
spire/doc/DocumentObjectCollection.py
spire/doc/DocumentObjectType.py
