Metadata-Version: 2.1
Name: Spire.Doc.Free
Version: 12.12.0
Summary: A 100% standalone Word Python API for Processing Word Files
Home-page: https://www.e-iceblue.com
Author: E-iceblue
Author-email: sales@e-iceblue.com
License: UNKNOWN
Platform: UNKNOWN
Classifier: Programming Language :: Python :: 3.6
Classifier: License :: Free To Use But Restricted
Classifier: License :: Other/Proprietary License
Classifier: Operating System :: Microsoft :: Windows
Classifier: Operating System :: POSIX :: Linux
Classifier: Operating System :: Unix
Requires-Python: >=3.7
Requires-Dist: plum-dispatch (==1.7.4)
